SecurityDelFile/SecurityDelFile.py
SecurityDelFile/__init__.py
SecurityDelFile-1.0.1.dist-info/METADATA
SecurityDelFile-1.0.1.dist-info/WHEEL
SecurityDelFile-1.0.1.dist-info/entry_points.txt
SecurityDelFile-1.0.1.dist-info/top_level.txt
SecurityDelFile-1.0.1.dist-info/RECORD
