Metadata-Version: 2.1
Name: SecurityDelFile
Version: 1.0.1
Summary: SecurityDelFile
Home-page: UNKNOWN
Author: liuzihao
License: UNKNOWN
Keywords: Security Del File app
Platform: UNKNOWN
Requires-Python: >=3
